setup.py
bluelake/__init__.py
bluelake/exc.py
bluelake.egg-info/PKG-INFO
bluelake.egg-info/SOURCES.txt
bluelake.egg-info/dependency_links.txt
bluelake.egg-info/not-zip-safe
bluelake.egg-info/requires.txt
bluelake.egg-info/top_level.txt
bluelake/client/__init__.py
bluelake/client/decorators.py
bluelake/client/exc.py
bluelake/client/rpc.py
bluelake/client/sdk.py
bluelake/client/sender.py
bluelake/protocol/__init__.py
bluelake/protocol/const.py
bluelake/protocol/protocol.py
bluelake/protocol/request.py
bluelake/protocol/response.py
bluelake/protocol/utils.py
bluelake/server/__init__.py
bluelake/server/exc.py
bluelake/server/http.py
bluelake/server/process.py
test/test_client.py
test/test_sdk.py
test/test_server.py
test/coffee_hr/IBuService.py
test/coffee_hr/IContactService.py
test/coffee_hr/IGroupService.py
test/coffee_hr/IPermissionService.py
test/coffee_hr/ISessionService.py
test/coffee_hr/IUserBuRoleService.py
test/coffee_hr/IUserService.py
test/coffee_hr/__init__.py