Metadata-Version: 1.0
Name: bluelake
Version: 1.1.1
Summary: Bluelake python client.
Home-page: UNKNOWN
Author: Eleme BPM
Author-email: bpm@ele.me
License: UNKNOWN
Platform: UNKNOWN
